odoo/addons/stock_packaging_usability_pp/README.rst
odoo/addons/stock_packaging_usability_pp/__init__.py
odoo/addons/stock_packaging_usability_pp/__manifest__.py
odoo/addons/stock_packaging_usability_pp/i18n/fr.po
odoo/addons/stock_packaging_usability_pp/i18n/it.po
odoo/addons/stock_packaging_usability_pp/i18n/stock_packaging_usability_pp.pot
odoo/addons/stock_packaging_usability_pp/models/__init__.py
odoo/addons/stock_packaging_usability_pp/models/product_packaging.py
odoo/addons/stock_packaging_usability_pp/models/stock_move.py
odoo/addons/stock_packaging_usability_pp/models/stock_quant_package.py
odoo/addons/stock_packaging_usability_pp/readme/CONFIGURE.rst
odoo/addons/stock_packaging_usability_pp/readme/CONTRIBUTORS.rst
odoo/addons/stock_packaging_usability_pp/readme/DESCRIPTION.rst
odoo/addons/stock_packaging_usability_pp/security/ir.model.access.csv
odoo/addons/stock_packaging_usability_pp/static/description/icon.png
odoo/addons/stock_packaging_usability_pp/static/description/index.html
odoo/addons/stock_packaging_usability_pp/views/product_packaging.xml
odoo/addons/stock_packaging_usability_pp/views/stock_move_line.xml
odoo/addons/stock_packaging_usability_pp/views/stock_picking.xml
odoo/addons/stock_packaging_usability_pp/views/stock_quant_package.xml
odoo/addons/stock_packaging_usability_pp/wizard/__init__.py
odoo/addons/stock_packaging_usability_pp/wizard/stock_select_product_packaging.py
odoo/addons/stock_packaging_usability_pp/wizard/stock_select_product_packaging_view.xml
odoo14_addon_stock_packaging_usability_pp-14.0.1.0.1.dev7.dist-info/METADATA
odoo14_addon_stock_packaging_usability_pp-14.0.1.0.1.dev7.dist-info/WHEEL
odoo14_addon_stock_packaging_usability_pp-14.0.1.0.1.dev7.dist-info/top_level.txt
odoo14_addon_stock_packaging_usability_pp-14.0.1.0.1.dev7.dist-info/RECORD
